cricket_tops/cricdata.py
cricket_tops-1.0.5.dist-info/LICENSE
cricket_tops-1.0.5.dist-info/METADATA
cricket_tops-1.0.5.dist-info/WHEEL
cricket_tops-1.0.5.dist-info/top_level.txt
cricket_tops-1.0.5.dist-info/RECORD
