Metadata-Version: 2.1
Name: cricket-tops
Version: 1.0.5
Summary: A Python package to view the top ODI, Tests, T20 ranked players (men and women) as well as Top Tests, ODI and T20 ranked teams.
Home-page: UNKNOWN
Author: Arghya Tarafdar
Author-email: arghya.tarafdar86@yahoo.co.in
License: MIT
Platform: UNKNOWN
Classifier: License :: OSI Approved :: MIT License
Classifier: Programming Language :: Python :: 3
Classifier: Programming Language :: Python :: 3.7
Requires-Dist: pandas
